rss_parse.py
setup.py
rss_parse.egg-info/PKG-INFO
rss_parse.egg-info/SOURCES.txt
rss_parse.egg-info/dependency_links.txt
rss_parse.egg-info/requires.txt
rss_parse.egg-info/top_level.txt