Metadata-Version: 1.1
Name: rss-parse
Version: 0.1.0b1
Summary: RSS feed parser: Takes a URL and configuration dict and returns an iterable object containing feed `<items>`
Home-page: https://github.com/dev-dull/rss_parse
Author: Alastair Drong
Author-email: adrong@gmail.com
License: MIT
Keywords: RSS parser xml news Atom
Platform: UNKNOWN
Classifier: Development Status :: 4 - Beta
Classifier: Intended Audience :: Developers
Classifier: Topic :: Software Development :: RSS and Atom feed parsing.
Classifier: License :: OSI Approved :: MIT License
Classifier: Programming Language :: Python :: 3.4
